scrape_do_nlp/__init__.py
scrape_do_nlp/main.py
scrape_do_nlp-1.0.2.dist-info/METADATA
scrape_do_nlp-1.0.2.dist-info/WHEEL
scrape_do_nlp-1.0.2.dist-info/top_level.txt
scrape_do_nlp-1.0.2.dist-info/RECORD
