Metadata-Version: 2.1
Name: scrape-do-nlp
Version: 1.0.2
Summary: This package will just take twitter keys and topic you want to scrape and give summarya dn sentiment as output
Home-page: https://github.com/eaglewarrior/scrape_do_nlp
Author: Rinki Nag
Author-email: accanymous@gmail.com
License: UNKNOWN
Keywords: python,first package
Platform: UNKNOWN
Classifier: Development Status :: 3 - Alpha
Classifier: Intended Audience :: Education
Classifier: Programming Language :: Python :: 2
Classifier: Programming Language :: Python :: 3
Classifier: Operating System :: MacOS :: MacOS X
Classifier: Operating System :: Microsoft :: Windows
Requires-Dist: requests
Requires-Dist: urllib
Requires-Dist: time
Requires-Dist: spacy
Requires-Dist: bs4
Requires-Dist: wordcloud
Requires-Dist: matplotlib
Requires-Dist: nltk
Requires-Dist: re
Requires-Dist: tweepy
Requires-Dist: textblob
Requires-Dist: pandas
Requires-Dist: numpy
Requires-Dist: gensim
